margin_community_strategies/3emaRsi.py
margin_community_strategies/__init__.py
margin_community_strategies-0.0.4.dist-info/LICENSE
margin_community_strategies-0.0.4.dist-info/METADATA
margin_community_strategies-0.0.4.dist-info/WHEEL
margin_community_strategies-0.0.4.dist-info/top_level.txt
margin_community_strategies-0.0.4.dist-info/RECORD
