Metadata-Version: 2.1
Name: margin-community-strategies
Version: 0.0.4
Summary: Strategies for the Margin Strategy Editor provided by the community
Home-page: https://github.com/MarginOpenSource/community-strategies
Author: Margin UG
Author-email: contact@margin.io
License: UNKNOWN
Platform: UNKNOWN
Classifier: Programming Language :: Python :: 3
Classifier: License :: OSI Approved :: MIT License
Classifier: Operating System :: OS Independent
Requires-Python: >=3.6
License-File: LICENSE
Requires-Dist: margin-strategy-sdk
